pyetchash.cpython-38-darwin.so
pyetchash-0.1.27.dist-info/METADATA
pyetchash-0.1.27.dist-info/WHEEL
pyetchash-0.1.27.dist-info/top_level.txt
pyetchash-0.1.27.dist-info/RECORD
